parcelforce_expresslink/__init__.py
parcelforce_expresslink/client/__init__.py
parcelforce_expresslink/client/alerts.py
parcelforce_expresslink/client/combadge.py
parcelforce_expresslink/client/request_response.py
parcelforce_expresslink/client/shipment_details.py
parcelforce_expresslink/config.py
parcelforce_expresslink/expresslink_api.wsdl
parcelforce_expresslink/expresslink_client.py
parcelforce_expresslink/models/__init__.py
parcelforce_expresslink/models/address.py
parcelforce_expresslink/models/base.py
parcelforce_expresslink/models/contact.py
parcelforce_expresslink/models/delivery_collection.py
parcelforce_expresslink/models/documents.py
parcelforce_expresslink/models/notifications.py
parcelforce_expresslink/models/parcel.py
parcelforce_expresslink/models/postoffice.py
parcelforce_expresslink/models/services.py
parcelforce_expresslink/models/shipment.py
parcelforce_expresslink-0.1.12.dist-info/WHEEL
parcelforce_expresslink-0.1.12.dist-info/entry_points.txt
parcelforce_expresslink-0.1.12.dist-info/METADATA
parcelforce_expresslink-0.1.12.dist-info/RECORD
