Metadata-Version: 2.3
Name: parcelforce-expresslink
Version: 0.1.12
Summary: Basic client for Parcelforce Expresslink API
Author: paw
Author-email: paw <pawrequest@users.noreply.github.com>
Requires-Dist: combadge==4.8.2
Requires-Dist: loguru==0.7.3
Requires-Dist: pydantic==2.11.9
Requires-Dist: pydantic-settings==2.11.0
Requires-Dist: thefuzz==0.22.1
Requires-Dist: zeep==4.3.2
Requires-Python: >=3.13
